external_issue_checker/__init__.py
external_issue_checker/cli.py
external_issue_checker/git_utils.py
external_issue_checker/parser.py
external_issue_checker/platform/__init__.py
external_issue_checker/platform/github_api.py
external_issue_checker/platform/gitlab_api.py
external_issue_checker/platform/types.py
external_issue_checker-0.1.0.dist-info/LICENSE
external_issue_checker-0.1.0.dist-info/METADATA
external_issue_checker-0.1.0.dist-info/WHEEL
external_issue_checker-0.1.0.dist-info/entry_points.txt
external_issue_checker-0.1.0.dist-info/RECORD
