Metadata-Version: 2.3
Name: external-issue-checker
Version: 0.1.0
Summary: Lists commits in a Git repository that refer to external issues and reports their status.
License: MIT
Keywords: git,issue-tracker,external-issues,commit-checker,issue-status
Author: Matthieu Viry
Author-email: matthieu.viry@cnrs.fr
Requires-Python: >=3.10,<4.0
Classifier: Development Status :: 4 - Beta
Classifier: License :: OSI Approved :: MIT License
Classifier: Natural Language :: English
Classifier: Programming Language :: Python :: 3
Classifier: Programming Language :: Python :: 3.10
Classifier: Programming Language :: Python :: 3.11
Classifier: Programming Language :: Python :: 3.12
Classifier: Programming Language :: Python :: 3.13
Classifier: Programming Language :: Python :: Implementation :: CPython
Classifier: Programming Language :: Python :: Implementation :: PyPy
Requires-Dist: gitpython (>=3.1,<4.0)
Requires-Dist: httpx (>=0.28,<0.29)
Requires-Dist: rich (>=14.0,<15.0)
Requires-Dist: typer[all] (>=0.16,<0.17)
Project-URL: Bug Tracker, https://github.com/mthh/external-issue-checker
Project-URL: Homepage, https://github.com/mthh/external-issue-checker
Project-URL: Repository, https://github.com/mthh/external-issue-checker
